matlab_proxy/__init__.py
matlab_proxy/app.py
matlab_proxy/app_state.py
matlab_proxy/constants.py
matlab_proxy/default_configuration.py
matlab_proxy/devel.py
matlab_proxy/settings.py
matlab_proxy/gui/__init__.py
matlab_proxy/gui/favicon.ico
matlab_proxy/gui/index.html
matlab_proxy/gui/manifest.json
matlab_proxy/gui/robots.txt
matlab_proxy/gui/static/__init__.py
matlab_proxy/gui/static/css/__init__.py
matlab_proxy/gui/static/css/index.BedVwcEg.css
matlab_proxy/gui/static/js/__init__.py
matlab_proxy/gui/static/js/index.pQwV1obF.js
matlab_proxy/gui/static/media/MATLAB-env-blur.NupTbPv_.png
matlab_proxy/gui/static/media/__init__.py
matlab_proxy/gui/static/media/glyphicons-halflings-regular.BKjkU69z.woff
matlab_proxy/gui/static/media/glyphicons-halflings-regular.BUJKDMgK.eot
matlab_proxy/gui/static/media/glyphicons-halflings-regular.CSehLiBc.svg
matlab_proxy/gui/static/media/glyphicons-halflings-regular.DrwTMapi.ttf
matlab_proxy/gui/static/media/glyphicons-halflings-regular.DzqM6ju8.woff2
matlab_proxy/gui/static/media/ico-header-account-hover.-jQHo6Wx.svg
matlab_proxy/gui/static/media/ico-header-account.CJCFoo5a.svg
matlab_proxy/gui/static/media/ico-sprite.DXGLgzq9.png
matlab_proxy/gui/static/media/mathworks-eps.CGNQALa9.ttf
matlab_proxy/gui/static/media/mathworks-eps.DrkCtQtG.svg
matlab_proxy/gui/static/media/mathworks-eps.Ds7lQbql.woff
matlab_proxy/gui/static/media/mathworks-pictograms.BdqxEfBR.woff
matlab_proxy/gui/static/media/mathworks-pictograms.CCLweoD4.svg
matlab_proxy/gui/static/media/mathworks-pictograms.DZhFdRSm.ttf
matlab_proxy/gui/static/media/mathworks.C-qsbhDy.svg
matlab_proxy/gui/static/media/mathworks.Ceplx86V.ttf
matlab_proxy/gui/static/media/mathworks.D08X1Vp8.woff
matlab_proxy/gui/static/media/trigger-error.QEdsGL-m.svg
matlab_proxy/gui/static/media/trigger-ok.Dzg8OIrk.svg
matlab_proxy/icons/matlab.svg
matlab_proxy/matlab/evaluateUserMatlabCode.m
matlab_proxy/matlab/startup.m
matlab_proxy/util/__init__.py
matlab_proxy/util/cookie_jar.py
matlab_proxy-0.30.1.dist-info/METADATA
matlab_proxy-0.30.1.dist-info/WHEEL
matlab_proxy-0.30.1.dist-info/entry_points.txt
matlab_proxy-0.30.1.dist-info/licenses/LICENSE.md
matlab_proxy-0.30.1.dist-info/RECORD
