Metadata-Version: 2.4
Name: matlab-proxy
Version: 0.30.1
Summary: Python® package enables you to launch MATLAB® and access it from a web browser.
Project-URL: Homepage, https://github.com/mathworks/matlab-proxy/
Project-URL: Documentation, https://github.com/mathworks/matlab-proxy/blob/main/README.md
Project-URL: Issues, https://github.com/mathworks/matlab-proxy/issues
Author-email: "The MathWorks Inc." <cloud@mathworks.com>
License-Expression: LicenseRef-MATHWORKS-CLOUD-REFERENCE-ARCHITECTURE-LICENSE
License-File: LICENSE.md
Keywords: MATLAB,MATLAB Javascript Desktop,MATLAB Proxy,MATLAB Web Desktop,Proxy,Remote MATLAB Web Access
Classifier: Intended Audience :: Developers
Classifier: Natural Language :: English
Classifier: Programming Language :: Python
Classifier: Programming Language :: Python :: 3.10
Classifier: Programming Language :: Python :: 3.11
Classifier: Programming Language :: Python :: 3.12
Classifier: Programming Language :: Python :: 3.13
Requires-Python: <3.14,>=3.10
Requires-Dist: aiohttp-session[secure]
Requires-Dist: aiohttp>=3.7.4
Requires-Dist: psutil
Requires-Dist: requests
Requires-Dist: rich
Requires-Dist: watchdog
Provides-Extra: dev
Requires-Dist: aiohttp-devtools; extra == 'dev'
Requires-Dist: black; extra == 'dev'
Requires-Dist: psutil; extra == 'dev'
Requires-Dist: pytest; extra == 'dev'
Requires-Dist: pytest-aiohttp; extra == 'dev'
Requires-Dist: pytest-asyncio; extra == 'dev'
Requires-Dist: pytest-cov; extra == 'dev'
Requires-Dist: pytest-env; extra == 'dev'
Requires-Dist: pytest-mock; extra == 'dev'
Requires-Dist: pytest-playwright; extra == 'dev'
Requires-Dist: pytest-timeout; extra == 'dev'
Requires-Dist: ruff; extra == 'dev'
Requires-Dist: urllib3; extra == 'dev'
Provides-Extra: test
Requires-Dist: psutil; extra == 'test'
Requires-Dist: pytest; extra == 'test'
Requires-Dist: pytest-aiohttp; extra == 'test'
Requires-Dist: pytest-asyncio; extra == 'test'
Requires-Dist: pytest-cov; extra == 'test'
Requires-Dist: pytest-env; extra == 'test'
Requires-Dist: pytest-mock; extra == 'test'
Requires-Dist: pytest-playwright; extra == 'test'
Requires-Dist: pytest-timeout; extra == 'test'
Requires-Dist: urllib3; extra == 'test'
